fptokens/__init__.py
fptokens-0.1.1.dist-info/DESCRIPTION.rst
fptokens-0.1.1.dist-info/LICENSE.txt
fptokens-0.1.1.dist-info/METADATA
fptokens-0.1.1.dist-info/RECORD
fptokens-0.1.1.dist-info/WHEEL
fptokens-0.1.1.dist-info/metadata.json
fptokens-0.1.1.dist-info/top_level.txt
