Metadata-Version: 2.0
Name: fptokens
Version: 0.1.1
Summary: A library for tokenisable filename paths
Home-page: https://github.com/florianeinfalt/fptokens
Author: Florian Einfalt
Author-email: info@florianeinfalt.de
License: Apache 2.0
Platform: UNKNOWN
Classifier: Development Status :: 3 - Alpha
Classifier: Intended Audience :: Developers
Classifier: Natural Language :: English
Classifier: Topic :: Software Development :: Build Tools
Classifier: License :: OSI Approved :: Apache Software License
Classifier: Programming Language :: Python
Classifier: Programming Language :: Python :: 2
Classifier: Programming Language :: Python :: 2.7
Classifier: Programming Language :: Python :: 3
Classifier: Programming Language :: Python :: 3.5
Classifier: Programming Language :: Python :: 3.6
Classifier: Programming Language :: Python :: Implementation :: CPython
Requires-Dist: attrs
Requires-Dist: path.py
